setup.cfg
setup.py
pyfsmlib/__init__.py
pyfsmlib/state_machine.py
pyfsmlib.egg-info/PKG-INFO
pyfsmlib.egg-info/SOURCES.txt
pyfsmlib.egg-info/dependency_links.txt
pyfsmlib.egg-info/top_level.txt