Metadata-Version: 1.1
Name: pyfsmlib
Version: 1.0
Summary: FSM for event driven applications
Home-page: https://github.com/jbarbadillo/pyFSM
Author: Javier Barbadillo
Author-email: javier.barbadillo@gmail.com
License: AGPL v3
Download-URL: https://github.com/jbarbadillo/pyFSM/archive/1.0.tar.gz
Keywords: fsm,state-machine
Platform: UNKNOWN
Classifier: Programming Language :: Python
Classifier: Programming Language :: Python :: 2.7
Classifier: Programming Language :: Python :: 3.2
Classifier: Programming Language :: Python :: 3.3
Classifier: Programming Language :: Python :: 3.4
Classifier: Programming Language :: Python :: 3.5
Classifier: Programming Language :: Python :: 3.6
